scrubadub_stanford/__init__.py
scrubadub_stanford/detectors/__init__.py
scrubadub_stanford/detectors/core_nlp.py
scrubadub_stanford/detectors/stanford.py
scrubadub_stanford/detectors/stanza.py
scrubadub_stanford/detectors/utils/__init__.py
scrubadub_stanford/detectors/utils/utils.py
scrubadub_stanford-2.1.3.dist-info/LICENSE
scrubadub_stanford-2.1.3.dist-info/METADATA
scrubadub_stanford-2.1.3.dist-info/WHEEL
scrubadub_stanford-2.1.3.dist-info/entry_points.txt
scrubadub_stanford-2.1.3.dist-info/top_level.txt
scrubadub_stanford-2.1.3.dist-info/RECORD
